euclidean_algorithm/__init__.py
euclidean_algorithm/euclidean_algorithm.py
euclidean_algorithm-1.0.2.dist-info/LICENSE
euclidean_algorithm-1.0.2.dist-info/METADATA
euclidean_algorithm-1.0.2.dist-info/WHEEL
euclidean_algorithm-1.0.2.dist-info/RECORD
