Metadata-Version: 2.1
Name: euclidean-algorithm
Version: 1.0.2
Summary: Небольшая библиотека для вычисления НОД двух чисел (алгоритм Евклида)
License: MIT
Author: Макс
Author-email: rumyantsev1m0s1@gmail.com
Requires-Python: >=3.12,<4.0
Classifier: License :: OSI Approved :: MIT License
Classifier: Programming Language :: Python :: 3
Classifier: Programming Language :: Python :: 3.12
Classifier: Programming Language :: Python :: 3.13
Requires-Dist: numba (>=0.60.0,<0.61.0)
Requires-Dist: twine (>=6.0.1,<7.0.0)
